qwen3_rerank_trainer/__init__.py
qwen3_rerank_trainer/py.typed
qwen3_rerank_trainer/data/__init__.py
qwen3_rerank_trainer/data/formatting.py
qwen3_rerank_trainer/data/sampling.py
qwen3_rerank_trainer/data/tokenization.py
qwen3_rerank_trainer/evaluation/__init__.py
qwen3_rerank_trainer/evaluation/api_client.py
qwen3_rerank_trainer/evaluation/cli.py
qwen3_rerank_trainer/evaluation/gpu_utils.py
qwen3_rerank_trainer/evaluation/metrics.py
qwen3_rerank_trainer/evaluation/mteb_runner.py
qwen3_rerank_trainer/evaluation/report.py
qwen3_rerank_trainer/evaluation/two_stage_eval.py
qwen3_rerank_trainer/inference/__init__.py
qwen3_rerank_trainer/inference/base.py
qwen3_rerank_trainer/inference/qwen_reranker.py
qwen3_rerank_trainer/losses/__init__.py
qwen3_rerank_trainer/losses/contrastive.py
qwen3_rerank_trainer/losses/lambda_loss.py
qwen3_rerank_trainer/losses/listwise.py
qwen3_rerank_trainer/losses/pairwise.py
qwen3_rerank_trainer/losses/pointwise.py
qwen3_rerank_trainer/rl/__init__.py
qwen3_rerank_trainer/rl/losses.py
qwen3_rerank_trainer/rl/rewards.py
qwen3_rerank_trainer/training/__init__.py
qwen3_rerank_trainer/training/cli.py
qwen3_rerank_trainer/training/collator.py
qwen3_rerank_trainer/training/dataset.py
qwen3_rerank_trainer/training/rl_cli.py
qwen3_rerank_trainer/training/rl_dataset.py
qwen3_rerank_trainer/training/rl_trainer.py
qwen3_rerank_trainer/training/sft_trainer.py
qwen3_rerank_trainer-0.1.4.dist-info/licenses/LICENSE
qwen3_rerank_trainer-0.1.4.dist-info/METADATA
qwen3_rerank_trainer-0.1.4.dist-info/WHEEL
qwen3_rerank_trainer-0.1.4.dist-info/entry_points.txt
qwen3_rerank_trainer-0.1.4.dist-info/top_level.txt
qwen3_rerank_trainer-0.1.4.dist-info/RECORD
