Metadata-Version: 2.4
Name: qwen3-rerank-trainer
Version: 0.1.4
Summary: Training and evaluation toolkit for Qwen3-Reranker
Author-email: wangjiaji <2586590669@qq.com>
Maintainer-email: wangjiaji <2586590669@qq.com>
License-Expression: MIT
Project-URL: Homepage, https://github.com/Dullne/qwen3-rerank-trainer
Project-URL: Repository, https://github.com/Dullne/qwen3-rerank-trainer
Project-URL: Documentation, https://github.com/Dullne/qwen3-rerank-trainer#readme
Project-URL: Issues, https://github.com/Dullne/qwen3-rerank-trainer/issues
Keywords: reranker,qwen,nlp,ranking,information-retrieval
Classifier: Development Status :: 3 - Alpha
Classifier: Intended Audience :: Developers
Classifier: Intended Audience :: Science/Research
Classifier: Programming Language :: Python :: 3
Classifier: Programming Language :: Python :: 3.10
Classifier: Programming Language :: Python :: 3.11
Classifier: Programming Language :: Python :: 3.12
Classifier: Topic :: Scientific/Engineering :: Artificial Intelligence
Requires-Python: >=3.10
License-File: LICENSE
Requires-Dist: torch>=2.0.0
Requires-Dist: numpy>=1.20.0
Requires-Dist: datasets>=2.0.0
Provides-Extra: inference
Requires-Dist: transformers>=4.40.0; extra == "inference"
Provides-Extra: eval
Requires-Dist: mteb>=1.0.0; extra == "eval"
Requires-Dist: tqdm>=4.60.0; extra == "eval"
Requires-Dist: requests>=2.28.0; extra == "eval"
Requires-Dist: aiohttp>=3.8.0; extra == "eval"
Provides-Extra: evalscope
Requires-Dist: mteb>=1.0.0; extra == "evalscope"
Requires-Dist: evalscope>=0.5.0; extra == "evalscope"
Requires-Dist: tqdm>=4.60.0; extra == "evalscope"
Requires-Dist: requests>=2.28.0; extra == "evalscope"
Provides-Extra: full
Requires-Dist: transformers>=4.40.0; extra == "full"
Requires-Dist: mteb>=1.0.0; extra == "full"
Requires-Dist: evalscope>=0.5.0; extra == "full"
Requires-Dist: peft>=0.10.0; extra == "full"
Requires-Dist: tqdm>=4.60.0; extra == "full"
Requires-Dist: requests>=2.28.0; extra == "full"
Requires-Dist: aiohttp>=3.8.0; extra == "full"
Provides-Extra: dev
Requires-Dist: pytest>=7.0.0; extra == "dev"
Requires-Dist: pytest-cov>=4.0.0; extra == "dev"
Requires-Dist: black>=23.0.0; extra == "dev"
Requires-Dist: ruff>=0.1.0; extra == "dev"
Requires-Dist: mypy>=1.0.0; extra == "dev"
Dynamic: license-file
